potemkin/__init__.py
potemkin/cloudformationstack.py
potemkin/configservice.py
potemkin/terraformresources.py
potemkin/utilities.py
potemkin_decorator-0.0.13.dist-info/LICENSE.md
potemkin_decorator-0.0.13.dist-info/METADATA
potemkin_decorator-0.0.13.dist-info/WHEEL
potemkin_decorator-0.0.13.dist-info/top_level.txt
potemkin_decorator-0.0.13.dist-info/RECORD
