Metadata-Version: 2.1
Name: potemkin-decorator
Version: 0.0.13
Summary: Decorator to help for AWS/boto integration testing in pytest
Home-page: https://github.com/stelligent/potemkin-decorator
Author: Eric Kascic
Author-email: eric.kascic@stelligent.com
License: MIT
Platform: UNKNOWN
Requires-Python: >=3.6
Requires-Dist: boto3 (==1.12.26)
